{
  "StoreService": {
    "host": "localhost",
    "port": 8080,
    "path": {
      "brand": "/api/brand",
      "checkBrandName": "/api/brand/exist",
      "login": "/api/administrator/login",
      "register": "/api/administrator",
      "checkUserName": "/api/administrator/exist/account",
      "checkCellphone": "/api/administrator/exist/cellphone",
      "checkEmail": "/api/administrator/exist/email",
      "category": "/api/category",
      "checkCategoryName": "/api/category/exist",
      "subCategory": "/api/subCategory",
      "subCategoryDistinct": "/api/subCategory/distinct",
      "checkSubCategoryName": "/api/subCategory/exist",
      "color":"/api/color",
      "checkColorName": "/api/color/exist",
      "size":"/api/size",
      "checkSizeName": "/api/size/exist",
      "material":"/api/material",
      "checkMaterialName": "/api/material/exist",
      "itemSeries":"/api/itemSeries",
      "checkItemSeriesName": "/api/itemSeries/exist",
      "province":"/api/province",
      "provinceForCountry":"/api/province/forCountry",
      "checkProvinceName": "/api/province/exist",
      "country":"/api/country",
      "checkCountryName": "/api/country/exist",
      "expressCompany":"/api/expressCompany",
      "checkCompanyName": "/api/expressCompany/exist",
      "city":"/api/city",
      "checkCityName": "/api/city/exist",
      "systemLog":"/api/systemLog",
      "administrator":"/api/administrator",
      "administratorApprove":"/api/administrator/approve",
      "checkAdministrator":"/api/administrator/exist/name",
      "item":"/api/item",
      "itemByCode":"/api/item/byCode",
      "itemGroup":"/api/itemGroup",
      "checkItemCode":"/api/item/exist",
      "checkItemName":"/api/item/exist",
      "image":"/api/image",
      "imageList":"/api/image/list",
      "itemReview":"/api/itemReview",
      "itemReviewCondition":"/api/itemReview/condition",
      "shoppingCart":"/api/shoppingCart",
      "shoppingCartCondition":"/api/shoppingCart/condition",
      "brandHot":"/api/brandHot",
      "customer": "/api/customer",
      "changeCustomerStatus": "/api/customer/changeStatus",
      "itemHot":"/api/itemHot",
      "itemPromotion":"/api/itemPromotion",
      "order":"/api/order",
      "changeExpressInfo":"/api/order/changeExpressInfo",
      "changeOrderStatus":"/api/order/changeStatus",
      "navigate":"/api/navigate"

    }
  }
}